clearml_mcp/clearml_mcp.py
clearml_mcp/py.typed
clearml_mcp-0.3.0.dist-info/METADATA
clearml_mcp-0.3.0.dist-info/WHEEL
clearml_mcp-0.3.0.dist-info/entry_points.txt
clearml_mcp-0.3.0.dist-info/licenses/LICENSE
clearml_mcp-0.3.0.dist-info/RECORD
