Metadata-Version: 2.4
Name: clearml-mcp
Version: 0.3.0
Summary: lightweight MCP server that interacts with the ClearML API
Project-URL: homepage, https://github.com/prassanna-ravishankar/clearml-mcp
Project-URL: repository, https://github.com/prassanna-ravishankar/clearml-mcp.git
Project-URL: documentation, https://prassanna-ravishankar.github.io/clearml-mcp
Project-URL: issues, https://github.com/prassanna-ravishankar/clearml-mcp/issues
Author-email: "Prass, The Nomadic Coder" <me@prassanna.io>
License: MIT License
License-File: LICENSE
Keywords: python
Classifier: Development Status :: 3 - Alpha
Classifier: Programming Language :: Python
Classifier: Programming Language :: Python :: 3
Classifier: Programming Language :: Python :: 3.10
Classifier: Programming Language :: Python :: 3.11
Classifier: Programming Language :: Python :: 3.12
Classifier: Programming Language :: Python :: 3.13
Classifier: Typing :: Typed
Requires-Python: <4,>=3.10
Requires-Dist: clearml>=1.16.0
Requires-Dist: fastmcp>=0.1.0
Requires-Dist: pydantic>=2.0.0
